clogistic/__init__.py
clogistic/_version.py
clogistic/clogistic.py
clogistic-0.3.0.dist-info/LICENSE
clogistic-0.3.0.dist-info/METADATA
clogistic-0.3.0.dist-info/WHEEL
clogistic-0.3.0.dist-info/top_level.txt
clogistic-0.3.0.dist-info/RECORD
